mip/__init__.py
mip/project.py
mip/shell.py
made_in_python-2024.0a0.dist-info/LICENSE
made_in_python-2024.0a0.dist-info/METADATA
made_in_python-2024.0a0.dist-info/WHEEL
made_in_python-2024.0a0.dist-info/top_level.txt
made_in_python-2024.0a0.dist-info/RECORD
