Metadata-Version: 2.1
Name: made-in-python
Version: 2024.0a0
Summary: A Python-based build system
Home-page: https://volartrix.xyz/mip-docs
Author: Nekodev
Author-email: info@volartrix.xyz
License: Apache 2.0
Keywords: buildsystem,c,c++,asm
License-File: LICENSE
